---
date: 2019-12-26
layout: default
title: lambda

---



# java lambda

Lambda表达式被编译成了一个静态方法

```java
public class StreamTest {
	public static void main(String[] args) {
    printString("hello lambda", (String s) -> System.out.println(s));
	}

public static void printString(String s, Print<String> print) {
    print.print(s);
}

@FunctionalInterface
interface Print<T> {
    public void print(T t);
}
```
```java
  public com.lxs.stream.StreamTest();
    descriptor: ()V
    flags: ACC_PUBLIC
    Code:
      stack=1, locals=1, args_size=1
         0: aload_0
         1: invokespecial #1                  // Method java/lang/Object."<init>":()V
         4: return
      LineNumberTable:
        line 7: 0

  public static void main(java.lang.String[]);
    descriptor: ([Ljava/lang/String;)V
    flags: ACC_PUBLIC, ACC_STATIC
    Code:
      stack=2, locals=1, args_size=1
         0: ldc           #2                  // String hello lambda
         2: invokedynamic #3,  0              // InvokeDynamic #0:print:()Lcom/lxs/stream/Print;
         7: invokestatic  #4                  // Method printString:(Ljava/lang/String;Lcom/lxs/stream/Print;)V
        10: return
      LineNumberTable:
        line 10: 0
        line 12: 10

  public static void printString(java.lang.String, com.lxs.stream.Print<java.lang.String>);
    descriptor: (Ljava/lang/String;Lcom/lxs/stream/Print;)V
    flags: ACC_PUBLIC, ACC_STATIC
    Code:
      stack=2, locals=2, args_size=2
         0: aload_1
         1: aload_0
         2: invokeinterface #5,  2            // InterfaceMethod com/lxs/stream/Print.print:(Ljava/lang/Object;)V
         7: return
      LineNumberTable:
        line 15: 0
        line 16: 7
    Signature: #19                          // (Ljava/lang/String;Lcom/lxs/stream/Print<Ljava/lang/String;>;)V

  private static void lambda$main$0(java.lang.String);
    descriptor: (Ljava/lang/String;)V
    flags: ACC_PRIVATE, ACC_STATIC, ACC_SYNTHETIC
    Code:
      stack=2, locals=1, args_size=1
         0: getstatic     #6                  // Field java/lang/System.out:Ljava/io/PrintStream;
         3: aload_0
         4: invokevirtual #7                  // Method java/io/PrintStream.println:(Ljava/lang/String;)V
         7: return
      LineNumberTable:
        line 10: 0
}
SourceFile: "StreamTest.java"
InnerClasses:
     public static final #58= #57 of #61; //Lookup=class java/lang/invoke/MethodHandles$Lookup of class java/lang/invoke/MethodHandles
BootstrapMethods:
  0: #27 invokestatic java/lang/invoke/LambdaMetafactory.metafactory:(Ljava/lang/invoke/MethodHandles$Lookup;Ljava/lang/String;Ljava/lang/invoke/MethodType;Ljava/lang/invoke/MethodType;Ljava/lang/invoke/MethodHandle;Ljava/lang/invoke/MethodType;)Ljava/lang/invoke/CallSite;
    Method arguments:
      #28 (Ljava/lang/Object;)V
      #29 invokestatic com/lxs/stream/StreamTest.lambda$main$0:(Ljava/lang/String;)V
      #30 (Ljava/lang/String;)V

```

## 函数式接口

```java
 @FunctionalInterface
 修饰符 interface 接口名称 {
    返回值类型 方法名称(可选参数信息);
    // 其他非抽象方法内容
 }

```

如果一个方法的参数是Lambda，那么这个参数的类型一定是函数式接口